readysignal/__init__.py
readysignal/readysignal.py
readysignal-1.5.3.dist-info/licenses/LICENSE
tests/__init__.py
tests/test_readysignal.py
readysignal-1.5.3.dist-info/METADATA
readysignal-1.5.3.dist-info/WHEEL
readysignal-1.5.3.dist-info/top_level.txt
readysignal-1.5.3.dist-info/RECORD
