Metadata-Version: 2.4
Name: readysignal
Version: 1.5.3
Summary: The API for readysignal.com
Home-page: https://github.com/rxa-io/readysignal
Author: Jess Brown
Author-email: jess.brown@rxa.io
License-File: LICENSE
Requires-Dist: requests>=2.24.0
Requires-Dist: pandas>=1.2.0
Dynamic: author
Dynamic: author-email
Dynamic: description
Dynamic: description-content-type
Dynamic: home-page
Dynamic: license-file
Dynamic: requires-dist
Dynamic: summary
